bitstory/__init__.py
bitstory/version.py
bitstory-0.1.4.dist-info/LICENSE
bitstory-0.1.4.dist-info/METADATA
bitstory-0.1.4.dist-info/WHEEL
bitstory-0.1.4.dist-info/top_level.txt
bitstory-0.1.4.dist-info/RECORD
