Metadata-Version: 2.1
Name: bitstory
Version: 0.1.4
Summary: A package for programmatic access to bitstory API
Home-page: https://github.com/bitstory-ai/bitstory-api
Author: Gunnar Pope
Author-email: gunnar@bitstory.ai
License: MIT
Classifier: Programming Language :: Python :: 3
Classifier: License :: OSI Approved :: MIT License
Classifier: Operating System :: OS Independent
Requires-Python: >=3.10
License-File: LICENSE
